[
  {
    "content": "“Hiç biriniz kendisi için arzu ettiğini kardeşi içinde arzu etmedikçe iman etmiş olmaz!”",
    "source": "Müslim 45/71",
    "id": 2,
    "created_date": 1645289857,
    "isPublished": false,
    "publish_date": null
  },
  {
    "content": "“Hiçbir kul, ben kendisine ehlinden, malından ve bütün insanlardan daha sevgili olmadıkça iman etmiş olmaz!”",
    "source": "Müslim 44/69",
    "id": 1,
    "created_date": 1645288532,
    "isPublished": false,
    "publish_date": null
  },
  {
    "content": "“Merhamet edenlere, Rahman olan Allah da merhamet eder. Sizler yeryüzü ahalisine merhamet edin ki, semada bulunan (Allah) da size merhamet etsin.”",
    "source": "Ebu Davud 4941, Tirmizi 1989",
    "id": 0,
    "created_date": 1645285146,
    "isPublished": true,
    "publish_date": null
  },
  {
    "content": "İki göz vardır ki, cehennem ateşi onlara dokunmaz: Allah korkusundan ağlayan göz, bir de gecesini Allah yolunda, nöbet tutarak geçiren göz.",
    "source": "Tirmizî, Fedâilü'l-Cihâd, 12",
    "id": 3,
    "created_date": 1645294533,
    "isPublished": false,
    "publish_date": null
  },
  {
    "content": "Müslüman, insanların elinden ve dilinden emin olduğu kimsedir.",
    "source": "Tirmizî, Îmân, 12; Nesâî, Îmân, 8",
    "id": 4,
    "created_date": 1645294938,
    "isPublished": false,
    "publish_date": null
  },
  {
    "content": "İman etmedikçe cennete giremezsiniz, birbirinizi sevmedikçe de (gerçek anlamda) iman etmiş olamazsınız.",
    "source": "Müslim, Îmân, 93; Tirmizî, Sıfâtu'l-Kıyâme, 56",
    "id": 5,
    "created_date": 1645295112,
    "isPublished": false,
    "publish_date": null
  },
  {
    "content": "Birbirinize buğuz etmeyin, birbirinize haset etmeyin, birbirinize arka çevirmeyin; ey Allah'ın kulları, kardeş olun. Bir müslümana, üç günden fazla (din) kardeşi ile dargın durması helal olmaz.",
    "source": "Buhârî, Edeb, 57, 58.",
    "id": 6,
    "created_date": 1645295375,
    "isPublished": false,
    "publish_date": null
  },
  {
    "content": "\"Kişinin, Müslüman kardeşini küçük görmesi kötülük olarak kendisine yeter.\"",
    "source": "(Müslim, Birr, 32)",
    "id": 7,
    "created_date": 1645295516,
    "isPublished": false,
    "publish_date": null
  },
  {
    "content": "\"Nerede olursan ol, Allah'a karşı sorumluluğunun bilincinde ol! Kötülüğün peşinden iyi bir şey yap ki onu yok etsin. İnsanlara da güzel ahlâka uygun biçimde davran!\"",
    "source": "Tirmizî, Birr, 55",
    "id": 8,
    "created_date": 1645304159,
    "isPublished": false,
    "publish_date": null
  },
  {
    "content": "Kendisi cehennem ateşine ve cehennem ateşi de kendisine haram olan kişiyi size bildireyim mi? Cana yakın, yumuşak huylu, kolaylaştırıcı kimse.",
    "source": "Tirmizî, Sıfatü'l-kıyâme, 45",
    "id": 9,
    "created_date": 1645304328,
    "isPublished": false,
    "publish_date": null
  },
  {
    "content": "Müminler birbirlerini sevmede, birbirlerine merhamet ve şefkat göstermede, tıpkı bir organı rahatsızlandığında diğer organları da uykusuzluk ve yüksek ateşle bu acıyı paylaşan bir bedene benzer.",
    "source": "Müslim, Birr, 66",
    "id": 10,
    "created_date": 1645304416,
    "isPublished": false,
    "publish_date": null
  },
  {
    "content": "Kim bir hayra delâlet ederse onu işleyen gibi ecir alır.",
    "source": "Beyhakî",
    "id": 11,
    "created_date": 1645304542,
    "isPublished": false,
    "publish_date": null
  },
  {
    "content": "Canın her istediğini yemek de israf cümlesindendir.",
    "source": "Ebû Dâvud",
    "id": 12,
    "created_date": 1645304626,
    "isPublished": false,
    "publish_date": null
  },
  {
    "content": "Ömrü uzun ve ameli hareketi, işi ve ibâdeti güzel olan kimseye ne mutlu!",
    "source": "Taberânî",
    "id": 13,
    "created_date": 1645304747,
    "isPublished": false,
    "publish_date": null
  },
  {
    "content": "Kabir azâbının çoğu idrardan temizlenmeye ehemmiyet vermemektendir.",
    "source": "İbn Mâce, Nesaî",
    "id": 14,
    "created_date": 1645304802,
    "isPublished": false,
    "publish_date": null
  },
  {
    "content": "Dişleri misvak ile temizlemek ölümden başka bütün hastalıkların mühim bir kısmına şifâdır.",
    "source": "Keşfü’l hafâ, Deylemî",
    "id": 15,
    "created_date": 1645304879,
    "isPublished": false,
    "publish_date": null
  },
  {
    "content": "Temizliğe itinâ ve devamlılık, insanı tam bir îmâna da’vet eder.",
    "source": "Taberânî",
    "id": 16,
    "created_date": 1645304968,
    "isPublished": false,
    "publish_date": null
  },
  {
    "content": "Namazda safları iyi doğrultunuz, yani bir hizâda ve muntazam tutunuz.",
    "source": "Müslim",
    "id": 17,
    "created_date": 1645305054,
    "isPublished": false,
    "publish_date": null
  }
]
